cross_db/__init__.py
cross_db/db.py
cross_db-1.0.0.dist-info/METADATA
cross_db-1.0.0.dist-info/WHEEL
cross_db-1.0.0.dist-info/RECORD
